{
    "welcome.label.welcome_message": "ยินดีต้อนรับสู่\\nCryptoplat !",
    "welcome.button.login": "เข้าสู่ระบบ",
    "welcome.button.create_account": "สร้างบัญชีใหม่",
    "welcome.label.minimum_requirement": "รองรับ Safari เวอร์ชัน 11 หรือสูงกว่า\\nChrome เวอร์ชัน 53 หรือสูงกว่า เพื่อการทำ KYC",
    "auth.label.email_field": "อีเมล์",
    "auth.placeholder.email_field": "อีเมล์",
    "auth.label.mobile_no_field": "เบอร์โทรศัพท์",
    "auth.placeholder.mobile_no_field": "เบอร์โทรศัพท์",
    "auth.label.not_us_citizen": "I am not a U.S. citizen and considered a ‘non-resident for tax purposes’.",
    "auth.label.agree_with_term_and_privacy": "I agree with this terms & conditions  and Privacy Policy / AML & CTPF Policy agreements.",
    "auth.label.receive_marketing_news": "I would like to receive marketing news, promotions, and any other information from Crypto and its affiliates.",
    "auth.label.password_field": "Password",
    "auth.label.forgot_password": "Forgot Password",
    "auth.button.login": "Login",
    "auth.label.do_not_have_account_yet": "Don’t have an account yet?",
    "auth.label.create_account": "Create Account",
    "auth.label.page_title_forgot_password": "Forgot Password",
    "auth.label.page_desc_forgot_password": "Please enter your email and we will send you a link to reset your password.",
    "auth.button.reset_my_password": "Reset My Password",
    "auth.label.forgot_password_success_title": "We just sent a password reset link to your email",
    "auth.label.forgot_password_success_desc": "To change your password, please press the link sent to",
    "general.button.next": "ต่อไป",
    "general.button.confirm": "ยืนยัน",
    "create_account.label.email_field": "อีเมล์",
    "create_account.placeholder.email_field": "อีเมล์",
    "create_account.label.mobile_no_field": "เบอร์โทรศัพท์",
    "create_account.label.agree_not_us_check": "I am not a U.S. citizen and considered a ‘non-resident for tax purposes’.",
    "create_account.label.agree_term_check": "I am not a U.S. citizen and considered a ‘non-resident for tax purposes’.",
    "create_account.label.agree_news_check": "I would like to receive marketing news, promotions, and any other information from Crypto and its affiliates.",
    "create_account.label.page_title": "Create Account",
    "user_verification.label.page_title": "User verification",
    "user_verification.label.enter_email_otp_desc": "Please enter the 6-digit code sent to",
    "user_verification.button.resend_email": "Resend email",
    "user_verification.label.timer": "( ภายใน %@ วินาที )",
    "user_verification.label.enter_phone_otp_desc": "Please enter the 6-digit code sent to",
    "user_verification.label.not_your_info": "Not your Information?",
    "user_verification.label.change_info": "Change Information",
    "user_verification.button.confirm": "Confirm",
    "create_password.label.page_title": "Create Password",
    "create_password.label.password_title": "Password",
    "create_password.placeholder.password_input": "Password",
    "create_password.label.confirm_password_title": "Confirm Password",
    "create_password.placeholder.confirm_password_input": "Confirm Password",
    "create_password.label.password_require_title": "Password Require :",
    "create_password.label.password_require_8_char": "Use at least 8 characters",
    "create_password.label.password_require_low_upper": "Use at least 1 lowercase and 1 uppercase character",
    "create_password.label.password_require_1_number": "Use at least 1 number",
    "create_password.label.password_require_special": "Use at least 1 special character",
    "create_password.button.next": "Next",
    "set_pin.label.page_set_pin_title": "Set Pin Number",
    "set_pin.label.page_set_pin_desc": "Please set up your 6 digits PIN using for log in and confirm transaction",
    "set_pin.label.pin_input_title": "Please set up your new PIN",
    "set_pin.button.reset": "Reset",
    "set_pin.button.next": "Next",
    "set_pin.label.page_confirm_pin_title": "Confirm Pin Number",
    "set_pin.label.page_confirm_pin_desc": "Please confirm your new PIN",
    "set_pin.label.face_id_title": "Enable Face ID / Touch ID",
    "set_pin.label.face_id_desc": "Do you want to enable Face ID / Touch ID \\nAuthentication?",
    "set_pin.button.yes": "ใช่",
    "set_pin.button.no": "ไม่",
    "create_account.label.success_title": "Account created\\nsuccessfully!",
    "create_account.label.can_expore": "You can now explore our site!",
    "create_account.label.next_step": "Next step:",
    "create_account.label.can_trading": "To start trading, we need some \\nfurther KYC verifications. ",
    "create_account.label.the_test": "( The test will take around 10 minutes )",
    "create_account.button.verify": "Verify Now",
    "create_account.button.later": "I’ll do it later",
    "ekyc_landing.label.subpage_title": "First, we need you to Follow these steps",
    "ekyc_landing.label.subpage_desc": "To start trading please complete these steps.",
    "ekyc_landing.label.id_verify": "Identity verification",
    "ekyc_landing.label.suite_test": "Suitability Test",
    "ekyc_landing.label.know_test": "Knowledge Test",
    "ekyc_landing.button.start": "Start",
    "ekyc_landing.button.cancel": "Cancel",
    "ekyc_citizen_select.label.page_title": "Identity verification",
    "ekyc_citizen_select.label.please": "Please select your citizen type",
    "ekyc_citizen_select.label.thai": "Thai citizen",
    "ekyc_citizen_select.label.foreigner": "Foreigner",
    "ekyc_citizen_select.button.next": "Next",
    "ekyc_citizen_select.label.please_prepare_th": "Please prepare the following :",
    "ekyc_citizen_select.label.idcard_title_th": "Your ID card",
    "ekyc_citizen_select.label.idcard_desc_th": "You'll be required to take a photo of \\nID card to identify your identity.",
    "ekyc_citizen_select.label.photo_title_th": "Photo-ready environment",
    "ekyc_citizen_select.label.photo_desc_th": "Please prepare a space with enough light \\nto ensure you can take a photo easily",
    "ekyc_citizen_select.label.personal_title_th": "Personal information",
    "ekyc_citizen_select.label.personal_desc_th": "Your personal information and your work \\nplace information will be required.",
    "ekyc_citizen_select.label.please_prepare_fr": "Please prepare the following :",
    "ekyc_citizen_select.label.idcard_title_fr": "Your Passport",
    "ekyc_citizen_select.label.idcard_desc_fr": "Please prepare your valid passport with at \\nleast 3 to 6 months of remaining validity.",
    "ekyc_citizen_select.label.photo_title_fr": "Photo-ready environment",
    "ekyc_citizen_select.label.photo_desc_fr": "Please prepare a space with enough light \\nto ensure you can take a photo easily",
    "ekyc_citizen_select.label.personal_title_fr": "Personal information",
    "ekyc_citizen_select.label.personal_desc_fr": "Your personal information and your work \\nplace information will be required.",
    "work_permit.label.page_title": "Personal Information",
    "work_permit.label.nationality": "Nationality",
    "work_permit.placeholder.selected_nationality": "Select your nationality",
    "work_permit.label.resident_status": "Thailand Residential Status",
    "work_permit.option.resident": "Resident",
    "work_permit.option.non_resident": "Non-Resident",
    "work_permit.label.date_of_birth": "Date of Birth ( Day / Month / Year )",
    "work_permit.placeholder.date_of_birth": "Date of Birth",
    "work_permit.button.next": "Next",
    "work_permit.label.important": "Important \\n• Passport must have at least 3 months remaining validity. \\n• Upload a photo of your work permit document issued by the government agency",
    "work_permit.label.upload_work_permit": "Upload a photo of your work permit document",
    "work_permit.label.update_file_support": "PDF, JPG, and PNG file supported \\nMaximum size %@ MB",
    "work_permit.label.file_upload": "Files Uploaded",
    "work_permit.label.no_file_upload": "No file uploaded",
    "work_permit.label.file_size": "File size: %@ MB",
    "work_permit.label.important_non": "Important \\n• Passport must have at least 6 months remaining validity.",
    "work_permit.label.age_warning_long": "Your age is below 20. Please recheck your Date of birth as the law require at least age of 20 to be able to trade.",
    "work_permit.label.age_warning_short": "Your age is below 20.",
    "ekyc_infomation.label.page_title": NaN,
    "ekyc_infomation.button.next": NaN,
    "ekyc_infomation.label.subpage_title": NaN,
    "ekyc_infomation.label.title_name_th": NaN,
    "ekyc_infomation.placeholder.title_name_th": NaN,
    "ekyc_infomation.label.fname_th": NaN,
    "ekyc_infomation.placeholder.fname_th": NaN,
    "ekyc_infomation.label.mname_th": NaN,
    "ekyc_infomation.placeholder.mname_th": NaN,
    "ekyc_infomation.label.lname_th": NaN,
    "ekyc_infomation.placeholder.lname_th": NaN,
    "ekyc_infomation.label.title_name_en": NaN,
    "ekyc_infomation.placeholder.title_name_en": NaN,
    "ekyc_infomation.label.fname_en": NaN,
    "ekyc_infomation.placeholder.fname_en": NaN,
    "ekyc_infomation.label.mname_en": NaN,
    "ekyc_infomation.placeholder.mname_en": NaN,
    "ekyc_infomation.label.lname_en": NaN,
    "ekyc_infomation.placeholder.lname_en": NaN,
    "ekyc_infomation.label.date_of_birth": NaN,
    "ekyc_infomation.placeholder.date_of_birth": NaN,
    "ekyc_infomation.label.idcard": NaN,
    "ekyc_infomation.placeholder.idcard": NaN,
    "ekyc_infomation.label.laser_code": NaN,
    "ekyc_infomation.placeholder.laser_code": NaN,
    "ekyc_infomation.label.date_of_issue": NaN,
    "ekyc_infomation.placeholder.date_of_issue": NaN,
    "ekyc_infomation.label.age_warning_long": "Your age is below 20. Please recheck your Date of birth as the law require at least age of 20 to be able to trade.",
    "ekyc_infomation.label.age_warning_short": "Your age is below 20."
}